MANIFEST.in
README.md
setup.py
src/djwc_polymer.py
src/djwc/__init__.py
src/djwc/apps.py
src/djwc/middleware.py
src/djwc.egg-info/PKG-INFO
src/djwc.egg-info/SOURCES.txt
src/djwc.egg-info/dependency_links.txt
src/djwc.egg-info/requires.txt
src/djwc.egg-info/top_level.txt
src/djwc/management/__init__.py
src/djwc/management/commands/__init__.py
src/djwc/management/commands/djwc.py
src/djwc_example/__init__.py
src/djwc_example/asgi.py
src/djwc_example/settings.py
src/djwc_example/urls.py
src/djwc_example/wsgi.py
src/djwc_example/templates/base.html