Metadata-Version: 2.1
Name: djwc
Version: 1.3.4
Summary: WebComponents for Django
Home-page: https://yourlabs.io/oss/djwc
Author: James Pic
Author-email: jamespic@gmail.com
License: MIT
Keywords: django webcomponents
Platform: UNKNOWN
Classifier: Development Status :: 1 - Planning
Classifier: Environment :: Web Environment
Classifier: Framework :: Django
Classifier: Intended Audience :: Developers
Classifier: License :: OSI Approved :: MIT License
Classifier: Operating System :: OS Independent
Classifier: Programming Language :: Python
Classifier: Programming Language :: Python :: 2
Classifier: Programming Language :: Python :: 3
Classifier: Topic :: Internet :: WWW/HTTP
Classifier: Topic :: Software Development :: Libraries :: Python Modules
Requires-Python: >=3
